libname/__init__.py
libname/hello.py
base_folder-0.0.1.dist-info/METADATA
base_folder-0.0.1.dist-info/WHEEL
base_folder-0.0.1.dist-info/top_level.txt
base_folder-0.0.1.dist-info/RECORD
